{
  "annotations": {
    "list": []
  },
  "editable": true,
  "fiscalYearStartMonth": 0,
  "graphTooltip": 0,
  "id": null,
  "links": [],
  "liveNow": false,
  "panels": [
    {
      "datasource": {
        "type": "prometheus",
        "uid": "emp-prometheus"
      },
      "fieldConfig": {
        "defaults": {
          "color": {
            "mode": "palette-classic"
          },
          "unit": "s"
        },
        "overrides": []
      },
      "gridPos": {
        "h": 8,
        "w": 12,
        "x": 0,
        "y": 0
      },
      "id": 1,
      "options": {
        "legend": {
          "calcs": [],
          "displayMode": "list",
          "placement": "bottom",
          "showLegend": true
        },
        "tooltip": {
          "mode": "multi",
          "sort": "none"
        }
      },
      "targets": [
        {
          "exemplar": false,
          "expr": "understanding_loop_latency_seconds{stat=\"p95\"}",
          "format": "time_series",
          "interval": "",
          "legendFormat": "{{loop}}",
          "refId": "A"
        }
      ],
      "title": "Understanding Loop Latency (p95)",
      "type": "timeseries"
    },
    {
      "datasource": {
        "type": "prometheus",
        "uid": "emp-prometheus"
      },
      "fieldConfig": {
        "defaults": {
          "color": {
            "mode": "thresholds"
          },
          "mappings": [
            {
              "options": {
                "from": 0,
                "result": {
                  "text": "PASS"
                },
                "to": 0
              },
              "type": "range"
            },
            {
              "options": {
                "from": 1,
                "result": {
                  "text": "WARN"
                },
                "to": 1
              },
              "type": "range"
            },
            {
              "options": {
                "from": 2,
                "result": {
                  "text": "FAIL"
                },
                "to": 10
              },
              "type": "range"
            }
          ],
          "thresholds": {
            "mode": "absolute",
            "steps": [
              {
                "color": "green",
                "value": null
              },
              {
                "color": "yellow",
                "value": 1
              },
              {
                "color": "red",
                "value": 2
              }
            ]
          },
          "unit": "short"
        },
        "overrides": []
      },
      "gridPos": {
        "h": 8,
        "w": 12,
        "x": 12,
        "y": 0
      },
      "id": 2,
      "options": {
        "colorMode": "value",
        "graphMode": "none",
        "justifyMode": "auto",
        "orientation": "horizontal",
        "reduceOptions": {
          "calcs": [
            "max"
          ],
          "fields": "",
          "values": false
        },
        "textMode": "auto"
      },
      "targets": [
        {
          "expr": "max by (loop) (understanding_loop_latency_status)",
          "format": "time_series",
          "instant": true,
          "legendFormat": "{{loop}}",
          "refId": "A"
        }
      ],
      "title": "Latency SLO Status",
      "transformations": [],
      "type": "stat"
    },
    {
      "datasource": {
        "type": "prometheus",
        "uid": "emp-prometheus"
      },
      "fieldConfig": {
        "defaults": {
          "color": {
            "mode": "palette-classic"
          },
          "unit": "s"
        },
        "overrides": []
      },
      "gridPos": {
        "h": 8,
        "w": 12,
        "x": 0,
        "y": 8
      },
      "id": 3,
      "options": {
        "legend": {
          "calcs": [],
          "displayMode": "list",
          "placement": "bottom",
          "showLegend": true
        },
        "tooltip": {
          "mode": "multi",
          "sort": "none"
        }
      },
      "targets": [
        {
          "expr": "drift_alert_freshness_seconds",
          "legendFormat": "{{alert}}",
          "refId": "A"
        }
      ],
      "title": "Drift Alert Freshness",
      "type": "timeseries"
    },
    {
      "datasource": {
        "type": "prometheus",
        "uid": "emp-prometheus"
      },
      "fieldConfig": {
        "defaults": {
          "color": {
            "mode": "thresholds"
          },
          "mappings": [
            {
              "options": {
                "from": 0,
                "result": {
                  "text": "PASS"
                },
                "to": 0
              },
              "type": "range"
            },
            {
              "options": {
                "from": 1,
                "result": {
                  "text": "WARN"
                },
                "to": 1
              },
              "type": "range"
            },
            {
              "options": {
                "from": 2,
                "result": {
                  "text": "FAIL"
                },
                "to": 10
              },
              "type": "range"
            }
          ],
          "thresholds": {
            "mode": "absolute",
            "steps": [
              {
                "color": "green",
                "value": null
              },
              {
                "color": "yellow",
                "value": 1
              },
              {
                "color": "red",
                "value": 2
              }
            ]
          }
        },
        "overrides": []
      },
      "gridPos": {
        "h": 8,
        "w": 12,
        "x": 12,
        "y": 8
      },
      "id": 4,
      "options": {
        "colorMode": "value",
        "graphMode": "none",
        "justifyMode": "auto",
        "orientation": "horizontal",
        "reduceOptions": {
          "calcs": [
            "max"
          ],
          "fields": "",
          "values": false
        },
        "textMode": "auto"
      },
      "targets": [
        {
          "expr": "max by (alert) (drift_alert_freshness_status)",
          "instant": true,
          "legendFormat": "{{alert}}",
          "refId": "A"
        }
      ],
      "title": "Drift Alert SLO Status",
      "type": "stat"
    },
    {
      "datasource": {
        "type": "prometheus",
        "uid": "emp-prometheus"
      },
      "fieldConfig": {
        "defaults": {
          "color": {
            "mode": "palette-classic"
          }
        },
        "overrides": []
      },
      "gridPos": {
        "h": 8,
        "w": 12,
        "x": 0,
        "y": 16
      },
      "id": 5,
      "options": {
        "legend": {
          "calcs": [],
          "displayMode": "list",
          "placement": "bottom",
          "showLegend": true
        },
        "tooltip": {
          "mode": "multi",
          "sort": "none"
        }
      },
      "targets": [
        {
          "expr": "replay_determinism_drift",
          "legendFormat": "{{probe}}",
          "refId": "A"
        }
      ],
      "title": "Replay Determinism Drift",
      "type": "timeseries"
    },
    {
      "datasource": {
        "type": "prometheus",
        "uid": "emp-prometheus"
      },
      "fieldConfig": {
        "defaults": {
          "color": {
            "mode": "thresholds"
          },
          "mappings": [
            {
              "options": {
                "from": 0,
                "result": {
                  "text": "PASS"
                },
                "to": 0
              },
              "type": "range"
            },
            {
              "options": {
                "from": 1,
                "result": {
                  "text": "WARN"
                },
                "to": 1
              },
              "type": "range"
            },
            {
              "options": {
                "from": 2,
                "result": {
                  "text": "FAIL"
                },
                "to": 10
              },
              "type": "range"
            }
          ],
          "thresholds": {
            "mode": "absolute",
            "steps": [
              {
                "color": "green",
                "value": null
              },
              {
                "color": "yellow",
                "value": 1
              },
              {
                "color": "red",
                "value": 2
              }
            ]
          }
        },
        "overrides": []
      },
      "gridPos": {
        "h": 8,
        "w": 12,
        "x": 12,
        "y": 16
      },
      "id": 6,
      "options": {
        "colorMode": "value",
        "graphMode": "none",
        "justifyMode": "auto",
        "orientation": "horizontal",
        "reduceOptions": {
          "calcs": [
            "max"
          ],
          "fields": "",
          "values": false
        },
        "textMode": "auto"
      },
      "targets": [
        {
          "expr": "max by (probe) (replay_determinism_status)",
          "instant": true,
          "legendFormat": "{{probe}}",
          "refId": "A"
        }
      ],
      "title": "Replay Determinism SLO Status",
      "type": "stat"
    }
  ],
  "refresh": "30s",
  "schemaVersion": 39,
  "style": "dark",
  "tags": [
    "emp",
    "observability"
  ],
  "templating": {
    "list": []
  },
  "time": {
    "from": "now-6h",
    "to": "now"
  },
  "timepicker": {
    "refresh_intervals": [
      "10s",
      "30s",
      "1m",
      "5m",
      "15m"
    ]
  },
  "timezone": "",
  "title": "EMP Observability SLOs",
  "uid": "emp-observability",
  "version": 1,
  "weekStart": ""
}
